japancode/__init__.py
japancode/codes/__init__.py
japancode/codes/isocode.py
japancode/codes/jiscode.py
japancode/codes/lgcode.py
japancode/data/municipalities.json
japancode/data/prefectures.json
japancode/names/__init__.py
japancode/names/kana_roman.py
japancode/region.py
japancode/utils.py
japancode-0.1.0.dist-info/LICENSE.txt
japancode-0.1.0.dist-info/METADATA
japancode-0.1.0.dist-info/WHEEL
japancode-0.1.0.dist-info/RECORD
