Metadata-Version: 2.1
Name: japancode
Version: 0.1.0
Summary: Python library for converting Japanese region names and codes.
Home-page: https://github.com/ozekik/japancode
License: MIT
Author: Kentaro Ozeki
Author-email: kentaro.ozeki+dev@gmail.com
Requires-Python: >=3.10,<4.0
Classifier: License :: OSI Approved :: MIT License
Classifier: Programming Language :: Python :: 3
Classifier: Programming Language :: Python :: 3.10
Classifier: Programming Language :: Python :: 3.11
Classifier: Programming Language :: Python :: 3.12
Project-URL: Repository, https://github.com/ozekik/japancode
